deeplc/__init__.py
deeplc/__main__.py
deeplc/_argument_parser.py
deeplc/_exceptions.py
deeplc/aa_comp_rel.csv
deeplc/deeplc.py
deeplc/feat_extractor.py
deeplc/gui.py
deeplc/plot.py
deeplc/trainl3.py
deeplc/baseline_performance/baseline_predictions.csv
deeplc/mods/full_hc_PXD005573_pub_1fd8363d9af9dcad3be7553c39396960.keras
deeplc/mods/full_hc_PXD005573_pub_8c22d89667368f2f02ad996469ba157e.keras
deeplc/mods/full_hc_PXD005573_pub_cb975cfdd4105f97efa0b3afffe075cc.keras
deeplc/package_data/gui_images/__init__.py
deeplc/package_data/gui_images/config_icon.png
deeplc/package_data/gui_images/deeplc_logo.png
deeplc/package_data/gui_images/program_icon.png
deeplc-3.1.13.dist-info/licenses/LICENSE
deeplc-3.1.13.dist-info/METADATA
deeplc-3.1.13.dist-info/WHEEL
deeplc-3.1.13.dist-info/entry_points.txt
deeplc-3.1.13.dist-info/top_level.txt
deeplc-3.1.13.dist-info/RECORD
