Metadata-Version: 2.4
Name: deeplc
Version: 3.1.13
Summary: DeepLC: Retention time prediction for (modified) peptides using Deep Learning.
Author: Niels Hulstaert, Arthur Declercq, Ralf Gabriels, Lennart Martens, Sven Degroeve
Author-email: Robbin Bouwmeester <robbin.bouwmeester@ugent.be>
License: Apache License
Project-URL: GitHub, https://github.com/compomics/deeplc
Project-URL: PyPi, https://pypi.org/project/deeplc/
Project-URL: CompOmics, https://www.compomics.com
Keywords: DeepLC,Proteomics,deep learning,peptides,retention time,prediction
Classifier: Intended Audience :: Science/Research
Classifier: License :: OSI Approved :: Apache Software License
Classifier: Operating System :: OS Independent
Classifier: Programming Language :: Python :: 3
Classifier: Topic :: Scientific/Engineering :: Bio-Informatics
Classifier: Development Status :: 5 - Production/Stable
Requires-Python: >=3.11
License-File: LICENSE
Requires-Dist: tensorflow<3,>=2.15.0
Requires-Dist: numpy>=1.17
Requires-Dist: pandas>=0.25
Requires-Dist: scikit-learn>=1.2.0
Requires-Dist: deeplcretrainer<2,>=1
Requires-Dist: psm_utils>=0.2.3
Provides-Extra: test
Requires-Dist: pytest; extra == "test"
Requires-Dist: matplotlib<4,>=3; extra == "test"
Provides-Extra: gui
Requires-Dist: gooey>=1.0; extra == "gui"
Provides-Extra: plot
Requires-Dist: plotly>=5; extra == "plot"
Provides-Extra: deepcallc
Requires-Dist: scikit-learn<2,>=0.24.0; extra == "deepcallc"
Dynamic: license-file
